julia_custom_area_calculator_dci.py
julia_custom_area_calculator_dci-0.0.1.dist-info/LICENSE
julia_custom_area_calculator_dci-0.0.1.dist-info/METADATA
julia_custom_area_calculator_dci-0.0.1.dist-info/WHEEL
julia_custom_area_calculator_dci-0.0.1.dist-info/top_level.txt
julia_custom_area_calculator_dci-0.0.1.dist-info/RECORD
